python_glmnet-2.6.1.dist-info/RECORD
python_glmnet-2.6.1.dist-info/WHEEL
python_glmnet-2.6.1.dist-info/METADATA
glmnet/util.py
glmnet/logistic.py
glmnet/linear.py
glmnet/__init__.py
glmnet/_glmnet.cpython-312-darwin.so
glmnet/doc.py
glmnet/errors.py
glmnet/scorer.py
glmnet/.dylibs/libgfortran.5.dylib
glmnet/.dylibs/libquadmath.0.dylib
glmnet/.dylibs/libgcc_s.1.1.dylib
