Metadata-Version: 2.1
Name: python_glmnet
Version: 2.6.1
Summary: Python wrapper for glmnet
Author-Email: Civis Analytics Inc <opensource@replicahq.com>
Classifier: Development Status :: 5 - Production/Stable
Classifier: Environment :: Console
Classifier: Programming Language :: Python
Classifier: Programming Language :: Python :: 3
Classifier: Programming Language :: Python :: 3.9
Classifier: Programming Language :: Python :: 3.10
Classifier: Programming Language :: Python :: 3.11
Classifier: Programming Language :: Python :: 3.1
Classifier: Programming Language :: Python :: 3.13
Classifier: Programming Language :: Python :: 3 :: Only
Classifier: Operating System :: OS Independent
Classifier: Intended Audience :: Developers
Classifier: Intended Audience :: Science/Research
Classifier: License :: OSI Approved :: GNU General Public License v2 (GPLv2)
Classifier: Topic :: Scientific/Engineering
Project-URL: homepage, https://github.com/replicahq/python-glmnet
Project-URL: repository, https://github.com/replicahq/python-glmnet
Requires-Python: >=3.10
Requires-Dist: numpy>=1.26.4
Requires-Dist: scikit-learn>=1.4.0
Requires-Dist: scipy>=1.12.0
Requires-Dist: joblib>=1.3.0
Requires-Dist: setuptools>=75.3.0
